enso/__init__.py
enso/__main__.py
enso/consts.py
enso/enso_nic.py
enso/ensogen.py
enso_nic-0.1.3.dist-info/LICENSE
enso_nic-0.1.3.dist-info/METADATA
enso_nic-0.1.3.dist-info/WHEEL
enso_nic-0.1.3.dist-info/entry_points.txt
enso_nic-0.1.3.dist-info/top_level.txt
enso_nic-0.1.3.dist-info/RECORD
