Metadata-Version: 2.1
Name: enso-nic
Version: 0.1.3
Summary: Python frontend for the Ensō NIC.
Home-page: https://github.com/crossroadsfpga/enso
Download-URL: https://github.com/crossroadsfpga/enso
Author: Hugo Sadok
Author-email: sadok@cmu.edu
License: BSD
Keywords: network,enso,nic
Classifier: Development Status :: 4 - Beta
Classifier: Intended Audience :: Science/Research
Classifier: License :: OSI Approved :: BSD License
Classifier: Natural Language :: English
Classifier: Programming Language :: Python
Classifier: Programming Language :: Python :: 3
Classifier: Programming Language :: Python :: 3.9
Classifier: Programming Language :: Python :: 3.10
Classifier: Programming Language :: Python :: 3.11
Classifier: Topic :: System :: Networking
Classifier: Topic :: System :: Systems Administration
Requires-Python: >=3.9
License-File: LICENSE
Requires-Dist: click (>=8.0)
Requires-Dist: netexp (==0.1.17)
Requires-Dist: scapy
